[
  {
    "id": "76585bca5453d06199428f406fb462af",
    "sport_key": "baseball_kbo",
    "sport_title": "KBO",
    "commence_time": "2026-07-21T09:30:31Z",
    "home_team": "KT Wiz",
    "away_team": "Doosan Bears",
    "bookmakers": [
      {
        "key": "fanduel",
        "title": "FanDuel",
        "last_update": "2026-07-21T13:54:07Z",
        "markets": [
          {
            "key": "h2h",
            "last_update": "2026-07-21T13:54:07Z",
            "outcomes": [
              {
                "name": "Doosan Bears",
                "price": 1000
              },
              {
                "name": "KT Wiz",
                "price": -3000
              }
            ]
          }
        ]
      },
      {
        "key": "fanatics",
        "title": "Fanatics",
        "last_update": "2026-07-21T13:52:31Z",
        "markets": [
          {
            "key": "h2h",
            "last_update": "2026-07-21T13:52:31Z",
            "outcomes": [
              {
                "name": "Doosan Bears",
                "price": 560
              },
              {
                "name": "KT Wiz",
                "price": -1400
              }
            ]
          }
        ]
      },
      {
        "key": "draftkings",
        "title": "DraftKings",
        "last_update": "2026-07-21T13:53:11Z",
        "markets": [
          {
            "key": "h2h",
            "last_update": "2026-07-21T13:53:11Z",
            "outcomes": [
              {
                "name": "Doosan Bears",
                "price": 750
              },
              {
                "name": "KT Wiz",
                "price": -2000
              }
            ]
          },
          {
            "key": "spreads",
            "last_update": "2026-07-21T13:53:11Z",
            "outcomes": [
              {
                "name": "Doosan Bears",
                "price": 1000,
                "point": -1.5
              },
              {
                "name": "KT Wiz",
                "price": -5000,
                "point": 1.5
              }
            ]
          }
        ]
      },
      {
        "key": "bovada",
        "title": "Bovada",
        "last_update": "2026-07-21T13:56:43Z",
        "markets": [
          {
            "key": "h2h",
            "last_update": "2026-07-21T13:56:43Z",
            "outcomes": [
              {
                "name": "Doosan Bears",
                "price": 375
              },
              {
                "name": "KT Wiz",
                "price": -625
              }
            ]
          },
          {
            "key": "spreads",
            "last_update": "2026-07-21T13:56:43Z",
            "outcomes": [
              {
                "name": "Doosan Bears",
                "price": 650,
                "point": -1.5
              },
              {
                "name": "KT Wiz",
                "price": -1600,
                "point": 1.5
              }
            ]
          },
          {
            "key": "totals",
            "last_update": "2026-07-21T13:56:43Z",
            "outcomes": [
              {
                "name": "Over",
                "price": 230,
                "point": 3.5
              },
              {
                "name": "Under",
                "price": -340,
                "point": 3.5
              }
            ]
          }
        ]
      },
      {
        "key": "williamhill_us",
        "title": "Caesars",
        "last_update": "2026-07-21T13:59:50Z",
        "markets": [
          {
            "key": "h2h",
            "last_update": "2026-07-21T13:59:50Z",
            "outcomes": [
              {
                "name": "Doosan Bears",
                "price": 550
              },
              {
                "name": "KT Wiz",
                "price": -1000
              }
            ]
          }
        ]
      }
    ]
  }
]