[
  {
    "id": "fb30113e43d113f1ace48b8563ba1ee9",
    "sport_key": "soccer_fifa_world_cup",
    "sport_title": "FIFA World Cup",
    "commence_time": "2026-07-19T19:05:00Z",
    "home_team": "Spain",
    "away_team": "Argentina",
    "bookmakers": [
      {
        "key": "fanduel",
        "title": "FanDuel",
        "last_update": "2026-07-19T20:30:00Z",
        "markets": [
          {
            "key": "h2h",
            "last_update": "2026-07-19T20:30:00Z",
            "outcomes": [
              {
                "name": "Argentina",
                "price": 340
              },
              {
                "name": "Spain",
                "price": 155
              },
              {
                "name": "Draw",
                "price": 125
              }
            ]
          }
        ]
      },
      {
        "key": "betrivers",
        "title": "BetRivers",
        "last_update": "2026-07-19T20:29:51Z",
        "markets": [
          {
            "key": "h2h",
            "last_update": "2026-07-19T20:29:51Z",
            "outcomes": [
              {
                "name": "Argentina",
                "price": 360
              },
              {
                "name": "Spain",
                "price": 145
              },
              {
                "name": "Draw",
                "price": 120
              }
            ]
          },
          {
            "key": "totals",
            "last_update": "2026-07-19T20:29:51Z",
            "outcomes": [
              {
                "name": "Over",
                "price": 143,
                "point": 1.5
              },
              {
                "name": "Under",
                "price": -200,
                "point": 1.5
              }
            ]
          }
        ]
      },
      {
        "key": "draftkings",
        "title": "DraftKings",
        "last_update": "2026-07-19T20:29:50Z",
        "markets": [
          {
            "key": "h2h",
            "last_update": "2026-07-19T20:29:50Z",
            "outcomes": [
              {
                "name": "Argentina",
                "price": 340
              },
              {
                "name": "Spain",
                "price": 150
              },
              {
                "name": "Draw",
                "price": 130
              }
            ]
          }
        ]
      },
      {
        "key": "fanatics",
        "title": "Fanatics",
        "last_update": "2026-07-19T20:29:23Z",
        "markets": [
          {
            "key": "h2h",
            "last_update": "2026-07-19T20:29:23Z",
            "outcomes": [
              {
                "name": "Argentina",
                "price": 330
              },
              {
                "name": "Spain",
                "price": 160
              },
              {
                "name": "Draw",
                "price": 125
              }
            ]
          }
        ]
      },
      {
        "key": "betmgm",
        "title": "BetMGM",
        "last_update": "2026-07-19T20:30:10Z",
        "markets": [
          {
            "key": "h2h",
            "last_update": "2026-07-19T20:30:10Z",
            "outcomes": [
              {
                "name": "Argentina",
                "price": 310
              },
              {
                "name": "Spain",
                "price": 160
              },
              {
                "name": "Draw",
                "price": 125
              }
            ]
          },
          {
            "key": "totals",
            "last_update": "2026-07-19T20:30:10Z",
            "outcomes": [
              {
                "name": "Over",
                "price": 145,
                "point": 1.5
              },
              {
                "name": "Under",
                "price": -185,
                "point": 1.5
              }
            ]
          }
        ]
      },
      {
        "key": "mybookieag",
        "title": "MyBookie.ag",
        "last_update": "2026-07-19T20:30:09Z",
        "markets": [
          {
            "key": "h2h",
            "last_update": "2026-07-19T20:30:09Z",
            "outcomes": [
              {
                "name": "Argentina",
                "price": 295
              },
              {
                "name": "Spain",
                "price": 140
              },
              {
                "name": "Draw",
                "price": 130
              }
            ]
          },
          {
            "key": "totals",
            "last_update": "2026-07-19T20:30:09Z",
            "outcomes": [
              {
                "name": "Over",
                "price": 130,
                "point": 1.5
              },
              {
                "name": "Under",
                "price": -167,
                "point": 1.5
              }
            ]
          }
        ]
      },
      {
        "key": "bovada",
        "title": "Bovada",
        "last_update": "2026-07-19T20:28:31Z",
        "markets": [
          {
            "key": "h2h",
            "last_update": "2026-07-19T20:28:31Z",
            "outcomes": [
              {
                "name": "Argentina",
                "price": 350
              },
              {
                "name": "Spain",
                "price": 150
              },
              {
                "name": "Draw",
                "price": 130
              }
            ]
          },
          {
            "key": "totals",
            "last_update": "2026-07-19T20:28:31Z",
            "outcomes": [
              {
                "name": "Over",
                "price": 140,
                "point": 1.5
              },
              {
                "name": "Under",
                "price": -170,
                "point": 1.5
              }
            ]
          }
        ]
      },
      {
        "key": "williamhill_us",
        "title": "Caesars",
        "last_update": "2026-07-19T20:28:46Z",
        "markets": [
          {
            "key": "h2h",
            "last_update": "2026-07-19T20:28:46Z",
            "outcomes": [
              {
                "name": "Argentina",
                "price": 330
              },
              {
                "name": "Spain",
                "price": 157
              },
              {
                "name": "Draw",
                "price": 134
              }
            ]
          }
        ]
      }
    ]
  }
]